{"points": [{"x": 180.31, "y": 241.18, "type": 512, "name": "basic eye left"}, {"x": 314.0, "y": 241.34, "type": 768, "name": "basic eye right"}, {"x": 151.85, "y": 243.24, "type": 1024, "name": "basic eye left outer"}, {"x": 342.04, "y": 243.04, "type": 1280, "name": "basic eye right outer"}, {"x": 209.83, "y": 243.58, "type": 1536, "name": "basic eye left inner"}, {"x": 285.16, "y": 244.27, "type": 1792, "name": "basic eye right inner"}, {"x": 183.59, "y": 371.88, "type": 2048, "name": "basic mouth left"}, {"x": 311.03, "y": 370.08, "type": 2304, "name": "basic mouth right"}, {"x": 246.25, "y": 329.02, "type": 2560, "name": "basic nose tip"}, {"x": 247.13, "y": 375.31, "type": 2816, "name": "basic mouth center"}, {"x": 167.78, "y": 202.35, "type": 3072, "name": "basic eyebrow left"}, {"x": 207.63, "y": 206.79, "type": 3328, "name": "basic eyebrow left inner corner"}, {"x": 138.42, "y": 211.15, "type": 3584, "name": "basic eyebrow left outer corner"}, {"x": 325.63, "y": 202.88, "type": 3840, "name": "basic eyebrow right"}, {"x": 281.36, "y": 207.1, "type": 4096, "name": "basic eyebrow right inner corner"}, {"x": 363.69, "y": 211.85, "type": 4352, "name": "basic eyebrow right outer corner"}, {"x": 251.85, "y": 486.34, "type": 4608, "name": "basic chin bottom"}, {"x": 108.76, "y": 328.19, "type": 4864, "name": "basic chin left"}, {"x": 399.55, "y": 319.88, "type": 5120, "name": "basic chin right"}, {"x": 210.55, "y": 327.5, "type": 5376, "name": "basic nose left"}, {"x": 284.49, "y": 326.04, "type": 5632, "name": "basic nose right"}, {"x": 112.26, "y": 326.92, "type": 65536, "name": "chin ear left"}, {"x": 120.26, "y": 363.43, "type": 131072, "name": "chin left 1"}, {"x": 133.76, "y": 397.86, "type": 196608, "name": "chin left 2"}, {"x": 154.22, "y": 428.94, "type": 262144, "name": "chin left 3"}, {"x": 179.39, "y": 455.88, "type": 327680, "name": "chin left 4"}, {"x": 208.69, "y": 477.84, "type": 393216, "name": "chin left 5"}, {"x": 244.55, "y": 484.85, "type": 458752, "name": "chin bottom"}, {"x": 282.0, "y": 478.71, "type": 524288, "name": "chin right 5"}, {"x": 315.35, "y": 458.04, "type": 589824, "name": "chin right 4"}, {"x": 344.61, "y": 431.76, "type": 655360, "name": "chin right 3"}, {"x": 368.23, "y": 400.58, "type": 720896, "name": "chin right 2"}, {"x": 383.46, "y": 365.06, "type": 786432, "name": "chin right 1"}, {"x": 391.45, "y": 326.59, "type": 851968, "name": "chin ear right"}, {"x": 395.82, "y": 288.12, "type": 917504, "name": "temple right 4"}, {"x": 397.82, "y": 248.58, "type": 983040, "name": "temple right 3"}, {"x": 396.84, "y": 221.6, "type": 1048576, "name": "temple right 2"}, {"x": 395.86, "y": 194.63, "type": 1114112, "name": "temple right 1"}, {"x": 382.1, "y": 176.55, "type": 1179648, "name": "temple right"}, {"x": 368.33, "y": 158.47, "type": 1245184, "name": "forehead right"}, {"x": 329.74, "y": 155.62, "type": 1310720, "name": "forehead 4"}, {"x": 289.89, "y": 154.83, "type": 1376256, "name": "forehead 3"}, {"x": 248.35, "y": 155.13, "type": 1441792, "name": "forehead middle"}, {"x": 208.2, "y": 157.17, "type": 1507328, "name": "forehead 2"}, {"x": 170.11, "y": 160.07, "type": 1572864, "name": "forehead 1"}, {"x": 133.56, "y": 164.89, "type": 1638400, "name": "forehead left"}, {"x": 120.6, "y": 183.2, "type": 1703936, "name": "temple left"}, {"x": 107.63, "y": 201.51, "type": 1769472, "name": "temple left 1"}, {"x": 106.58, "y": 227.33, "type": 1835008, "name": "temple left 2"}, {"x": 105.54, "y": 253.16, "type": 1900544, "name": "temple left 3"}, {"x": 107.47, "y": 290.49, "type": 1966080, "name": "temple left 4"}, {"x": 346.81, "y": 243.16, "type": 2031616, "name": "eye right outer"}, {"x": 331.97, "y": 249.69, "type": 2097152, "name": "eye right bottom outer"}, {"x": 319.3, "y": 250.62, "type": 2162688, "name": "eye right bottom"}, {"x": 306.24, "y": 249.66, "type": 2228224, "name": "eye right bottom inner"}, {"x": 289.64, "y": 245.17, "type": 2293760, "name": "eye right inner"}, {"x": 305.2, "y": 234.1, "type": 2359296, "name": "eye right top inner"}, {"x": 318.57, "y": 229.52, "type": 2424832, "name": "eye right top"}, {"x": 331.92, "y": 234.14, "type": 2490368, "name": "eye right top outer"}, {"x": 158.55, "y": 243.06, "type": 2555904, "name": "eye left outer"}, {"x": 174.0, "y": 234.01, "type": 2621440, "name": "eye left top outer"}, {"x": 187.03, "y": 229.92, "type": 2686976, "name": "eye left top"}, {"x": 200.18, "y": 233.28, "type": 2752512, "name": "eye left top inner"}, {"x": 215.86, "y": 244.36, "type": 2818048, "name": "eye left inner"}, {"x": 199.49, "y": 248.85, "type": 2883584, "name": "eye left bottom inner"}, {"x": 186.29, "y": 249.71, "type": 2949120, "name": "eye left bottom"}, {"x": 174.21, "y": 249.42, "type": 3014656, "name": "eye left bottom outer"}, {"x": 279.61, "y": 215.42, "type": 3080192, "name": "eyebrow right inner"}, {"x": 294.96, "y": 199.39, "type": 3145728, "name": "eyebrow right top inner"}, {"x": 324.93, "y": 193.9, "type": 3211264, "name": "eyebrow right top"}, {"x": 351.38, "y": 199.88, "type": 3276800, "name": "eyebrow right top outer"}, {"x": 366.49, "y": 219.81, "type": 3342336, "name": "eyebrow right outer"}, {"x": 346.05, "y": 215.23, "type": 3407872, "name": "eyebrow right bottom outer"}, {"x": 324.76, "y": 212.16, "type": 3473408, "name": "eyebrow right botom"}, {"x": 301.8, "y": 216.11, "type": 3538944, "name": "eyebrow rigth bottom inner"}, {"x": 213.96, "y": 208.36, "type": 3604480, "name": "eyebrow left inner"}, {"x": 199.76, "y": 194.69, "type": 3670016, "name": "eyebrow left top inner"}, {"x": 172.96, "y": 191.55, "type": 3735552, "name": "eyebrow left top"}, {"x": 150.36, "y": 198.56, "type": 3801088, "name": "eyebrow left top outer"}, {"x": 139.0, "y": 216.9, "type": 3866624, "name": "eyebrow left outer"}, {"x": 156.05, "y": 211.69, "type": 3932160, "name": "eyebrow left bottom outer"}, {"x": 174.17, "y": 207.66, "type": 3997696, "name": "eyebrow left bottom"}, {"x": 194.34, "y": 209.73, "type": 4063232, "name": "eyebrow left bottom inner"}, {"x": 187.09, "y": 372.64, "type": 4128768, "name": "mouth left"}, {"x": 233.81, "y": 367.76, "type": 4194304, "name": "mouth left top"}, {"x": 252.02, "y": 371.99, "type": 4259840, "name": "mouth top"}, {"x": 270.37, "y": 367.59, "type": 4325376, "name": "mouth right top"}, {"x": 318.46, "y": 372.69, "type": 4390912, "name": "mouth right"}, {"x": 276.01, "y": 405.9, "type": 4456448, "name": "mouth right bottom"}, {"x": 252.37, "y": 409.61, "type": 4521984, "name": "mouth bottom"}, {"x": 228.84, "y": 406.08, "type": 4587520, "name": "mouth left bottom"}, {"x": 232.27, "y": 246.59, "type": 4653056, "name": "nose left top"}, {"x": 225.51, "y": 289.83, "type": 4718592, "name": "nose left top inner"}, {"x": 210.74, "y": 312.27, "type": 4784128, "name": "nose left top outer"}, {"x": 214.74, "y": 333.38, "type": 4849664, "name": "nose left bottom outer"}, {"x": 231.22, "y": 336.09, "type": 4915200, "name": "nose left bottom inner"}, {"x": 251.61, "y": 345.07, "type": 4980736, "name": "nose bottom"}, {"x": 272.12, "y": 335.72, "type": 5046272, "name": "nose right bottom inner"}, {"x": 288.84, "y": 332.85, "type": 5111808, "name": "nose right bottom outer"}, {"x": 292.56, "y": 311.17, "type": 5177344, "name": "nose right top outer"}, {"x": 277.26, "y": 289.07, "type": 5242880, "name": "nose right top inner"}, {"x": 268.83, "y": 246.02, "type": 5308416, "name": "nose right top"}, {"x": 320.49, "y": 239.73, "type": 5373952, "name": "eye right iris"}, {"x": 187.67, "y": 238.9, "type": 5439488, "name": "eye left iris"}, {"x": 250.67, "y": 319.6, "type": 5505024, "name": "nose tip"}, {"x": 178.45, "y": 360.18, "type": 5570560, "name": "cheekbone left"}, {"x": 329.03, "y": 355.83, "type": 5636096, "name": "cheekbone right"}, {"x": 249.97, "y": 236.52, "type": 5701632, "name": "nose bridge top"}, {"x": 249.52, "y": 265.87, "type": 5767168, "name": "nose bridge middle"}, {"x": 249.09, "y": 294.98, "type": 5832704, "name": "nose bridge bottom"}, {"x": 210.9, "y": 370.73, "type": 5898240, "name": "mouth left top point 1"}, {"x": 208.2, "y": 393.52, "type": 5963776, "name": "mouth left bottom point 1"}, {"x": 297.11, "y": 393.24, "type": 6029312, "name": "mouth right bottom point 1"}, {"x": 293.93, "y": 370.41, "type": 6094848, "name": "mouth right top point 1"}, {"x": 196.34, "y": 373.9, "type": 6160384, "name": "mouth inner left"}, {"x": 234.51, "y": 390.1, "type": 6225920, "name": "mouth inner left bottom"}, {"x": 252.28, "y": 392.71, "type": 6291456, "name": "mouth inner bottom"}, {"x": 270.05, "y": 390.36, "type": 6356992, "name": "mouth inner right bottom"}, {"x": 308.93, "y": 374.39, "type": 6422528, "name": "mouth inner right"}, {"x": 269.64, "y": 376.6, "type": 6488064, "name": "mouth inner right top"}, {"x": 252.28, "y": 378.72, "type": 6553600, "name": "mouth inner top"}, {"x": 234.94, "y": 376.41, "type": 6619136, "name": "mouth inner left top"}], "tags": {"5oclock shadow": {"value": "yes", "confidence": 0.69}, "age": {"value": "25", "confidence": 0.6}, "arched eyebrows": {"value": "no", "confidence": 0.01}, "attractive": {"value": "yes", "confidence": 0.07}, "bags under eyes": {"value": "yes", "confidence": 0.25}, "bald": {"value": "yes", "confidence": 0.54}, "bangs": {"value": "no", "confidence": 1.0}, "beard": {"value": "yes", "confidence": 1.0}, "big lips": {"value": "yes", "confidence": 0.3}, "big nose": {"value": "yes", "confidence": 0.74}, "black hair": {"value": "no", "confidence": 0.44}, "blond hair": {"value": "no", "confidence": 0.64}, "blurry": {"value": "no", "confidence": 1.0}, "brown hair": {"value": "no", "confidence": 0.69}, "bushy eyebrows": {"value": "yes", "confidence": 0.5}, "chubby": {"value": "yes", "confidence": 0.01}, "double chin": {"value": "no", "confidence": 0.01}, "expression": {"value": "smile", "confidence": 1.0}, "gender": {"value": "male", "confidence": 0.93}, "glasses": {"value": "no", "confidence": 1.0}, "goatee": {"value": "yes", "confidence": 1.0}, "gray hair": {"value": "no", "confidence": 0.44}, "heavy makeup": {"value": "no", "confidence": 0.93}, "high cheekbones": {"value": "yes", "confidence": 0.43}, "mouth open": {"value": "yes", "confidence": 0.68}, "mustache": {"value": "yes", "confidence": 0.8}, "narrow eyes": {"value": "no", "confidence": 0.78}, "oval face": {"value": "yes", "confidence": 0.81}, "pale skin": {"value": "no", "confidence": 0.6}, "pitch": {"value": "-8.87", "confidence": 1.0}, "pointy nose": {"value": "no", "confidence": 0.34}, "race": {"value": "white", "confidence": 1.0}, "receding hairline": {"value": "yes", "confidence": 0.86}, "rosy cheeks": {"value": "no", "confidence": 0.78}, "sideburns": {"value": "yes", "confidence": 0.83}, "straight hair": {"value": "no", "confidence": 0.64}, "wavy hair": {"value": "no", "confidence": 0.87}, "wearing earrings": {"value": "no", "confidence": 0.57}, "wearing hat": {"value": "no", "confidence": 0.47}, "wearing lipstick": {"value": "no", "confidence": 0.9}, "wearing necklace": {"value": "no", "confidence": 0.79}, "wearing necktie": {"value": "no", "confidence": 0.01}, "yaw": {"value": "5.02", "confidence": 1.0}, "young": {"value": "yes", "confidence": 0.49}}, "name": "face452.jpg"}